opentelemetry_hook_sampler/__init__.py
opentelemetry_hook_sampler/test_multiple_spans.py
opentelemetry_hook_sampler/test_single_span.py
opentelemetry_hook_sampler-0.0.3.dist-info/LICENSE
opentelemetry_hook_sampler-0.0.3.dist-info/METADATA
opentelemetry_hook_sampler-0.0.3.dist-info/WHEEL
opentelemetry_hook_sampler-0.0.3.dist-info/top_level.txt
opentelemetry_hook_sampler-0.0.3.dist-info/RECORD
